puzzlegen/frontend.py
puzzlegen/core/__init__.py
puzzlegen/core/batch_generator.py
puzzlegen/core/bfs_solver.py
puzzlegen/core/block.py
puzzlegen/core/grid_initializer.py
puzzlegen/core/puzzle_logic.py
puzzlegen/core/utils.py
puzzlegen-0.1.11.dist-info/licenses/LICENSE
puzzlegen-0.1.11.dist-info/METADATA
puzzlegen-0.1.11.dist-info/WHEEL
puzzlegen-0.1.11.dist-info/top_level.txt
puzzlegen-0.1.11.dist-info/RECORD
