Metadata-Version: 2.4
Name: puzzlegen
Version: 0.1.11
Summary: Procedural Match-3 Puzzle Generator and Solver
Author-email: Caroline DAKOURE <caroline.dakoure@umontreal.ca>, Katie LAVIGNE <katie.lavigne@mcgill.ca>
Project-URL: Homepage, https://github.com/carodak/puzzlegen
Project-URL: Issues, https://github.com/carodak/puzzlegen/issues
Classifier: Programming Language :: Python :: 3
Classifier: License :: OSI Approved :: GNU General Public License v3 (GPLv3)
Classifier: Operating System :: OS Independent
Requires-Python: >=3.8
License-File: LICENSE
Requires-Dist: matplotlib==3.10.8
Requires-Dist: tqdm==4.67.1
Dynamic: license-file
